kahi_openalex_sources/Kahi_openalex_sources.py
kahi_openalex_sources/__init__.py
kahi_openalex_sources/_version.py
Kahi_openalex_sources-0.1.2b0.dist-info/LICENSE
Kahi_openalex_sources-0.1.2b0.dist-info/METADATA
Kahi_openalex_sources-0.1.2b0.dist-info/WHEEL
Kahi_openalex_sources-0.1.2b0.dist-info/top_level.txt
Kahi_openalex_sources-0.1.2b0.dist-info/RECORD
