Metadata-Version: 2.1
Name: Kahi_openalex_sources
Version: 0.1.2b0
Summary: Kahi plugin to insert and update the sources from openalex
Home-page: https://github.com/colav/Kahi_plugins
Author: Colav
Author-email: colav@udea.edu.co
License: BSD
License-File: LICENSE
Requires-Dist: kahi
Requires-Dist: pymongo
Requires-Dist: joblib
